cvmutils/__init__.py
cvmutils/azdisk.py
cvmutils/cvmencryptimage.py
cvmutils/efi.py
cvmutils/guid.py
cvmutils/pcr.py
cvmutils/pe.py
cvmutils/reseal.py
cvmutils/sb.py
cvmutils/tools.py
cvmutils-0.1.7.dist-info/licenses/COPYING
cvmutils-0.1.7.dist-info/METADATA
cvmutils-0.1.7.dist-info/WHEEL
cvmutils-0.1.7.dist-info/entry_points.txt
cvmutils-0.1.7.dist-info/top_level.txt
cvmutils-0.1.7.dist-info/RECORD
