Metadata-Version: 2.4
Name: cvmutils
Version: 0.1.7
Summary: Tools for confidential virtual machines
Author: Vitaly Kuznetsov
Author-email: vkuznets@redhat.com
License: LGPL-2.1-or-later
Project-URL: GitLab, https://gitlab.com/vkuznets/cvmutils/
Keywords: CVM
License-File: COPYING
Requires-Dist: setuptools; python_version < "3.13"
Dynamic: license-file
